privacyschema/__init__.py
privacyschema/audit.py
privacyschema/consent.py
privacyschema/masking.py
privacyschema/retention.py
privacyschema/validation.py
privacyschema-0.3.0.dist-info/METADATA
privacyschema-0.3.0.dist-info/WHEEL
privacyschema-0.3.0.dist-info/top_level.txt
privacyschema-0.3.0.dist-info/RECORD
