Metadata-Version: 2.1
Name: privacyschema
Version: 0.3.0
Summary: Pluggable framework for personal data compliance (LGPD/GDPR)
Home-page: https://github.com/julioamorimdev/PrivacySchema
Author: Julio Amorim
Author-email: julio@grupojpc.com.br
License: MIT
Platform: UNKNOWN
Classifier: Programming Language :: Python :: 3
Classifier: License :: OSI Approved :: MIT License
Classifier: Operating System :: OS Independent
Classifier: Intended Audience :: Developers
Classifier: Topic :: Security
Classifier: Topic :: Software Development :: Libraries
Requires-Python: >=3.6
